openaicg2/__init__.py
openaicg2/forcefield/__init__.py
openaicg2/forcefield/aicgmodel.py
openaicg2/forcefield/amyloid.xml
openaicg2/forcefield/simulationsystem.py
openaicg2/forcefield/__pycache__/__init__.cpython-312.pyc
openaicg2/forcefield/__pycache__/aicg_idp_model.cpython-312.pyc
openaicg2/forcefield/__pycache__/aicgmodel.cpython-312.pyc
openaicg2/forcefield/__pycache__/simulationsystem.cpython-312.pyc
openaicg2/forcefield/functionterms/__init__.py
openaicg2/forcefield/functionterms/angle_terms.py
openaicg2/forcefield/functionterms/bond_terms.py
openaicg2/forcefield/functionterms/dihedral_terms.py
openaicg2/forcefield/functionterms/nonbonded_terms.py
openaicg2/forcefield/functionterms/umbrella_sampling.py
openaicg2/forcefield/para/2nao_9chain_l1p0_1p02p2_cb2p2_full_def_0_fib_to_openmm.info
openaicg2/forcefield/para/2nao_9chain_l1p0_1p02p2_cb2p2_full_def_0_to_openmm.info
openaicg2/forcefield/para/2nao_9chain_l1p0_1p02p2_cb2p2_full_def_0_to_openmm_correctgo.info
openaicg2/forcefield/para/exv.para
openaicg2/forcefield/para/flexible_local_abeta.para
openaicg2/forcefield/para/kh.para
openaicg2/forcefield/para/protein_constanst.py
openaicg2/utils/__init__.py
openaicg2/utils/gene_psf.py
openaicg2/utils/parser_exv_params.py
openaicg2/utils/parser_flp_para.py
openaicg2/utils/parser_kh_params.py
openaicg2/utils/parser_ninfo.py
openaicg2/utils/redefinetop.py
openaicg2-0.0.1.dist-info/LICENSE
openaicg2-0.0.1.dist-info/METADATA
openaicg2-0.0.1.dist-info/WHEEL
openaicg2-0.0.1.dist-info/top_level.txt
openaicg2-0.0.1.dist-info/RECORD
