Metadata-Version: 2.1
Name: openaicg2
Version: 0.0.1
Summary: A coarse-grained molecular model of protein
Author-email: ZouLuJun <zoulujun@ucas.ac.cn>
Project-URL: Homepage, https://gowindyer.github.io/openaicgdoc
Classifier: Programming Language :: Python :: 3
Classifier: License :: OSI Approved :: MIT License
Classifier: Operating System :: OS Independent
Requires-Python: >=3.8
License-File: LICENSE
Requires-Dist: numpy
Requires-Dist: pandas
Requires-Dist: mdtraj
Requires-Dist: OpenMM
